mpl_tools/__init__.py
mpl_tools/conftest.py
mpl_tools/log_toggler.py
mpl_tools/misc.py
mpl_tools/place.py
mpl_tools/place_ax.py
mpl_tools/sci.py
mpl_tools/visibility.py
mpl_tools-0.4.0.dist-info/METADATA
mpl_tools-0.4.0.dist-info/WHEEL
mpl_tools-0.4.0.dist-info/RECORD
