Metadata-Version: 2.1
Name: mpl-tools
Version: 0.4.0
Summary: Tools for working with matplotlib
Home-page: https://github.com/patricknraanes/mpl-tools
License: MIT
Keywords: matplotlib,plotting
Author: patricknraanes
Author-email: patrick.n.raanes@gmail.com
Requires-Python: >=3.9,<4.0
Classifier: License :: OSI Approved :: MIT License
Classifier: Programming Language :: Python :: 3
Classifier: Programming Language :: Python :: 3.9
Classifier: Programming Language :: Python :: 3.10
Classifier: Programming Language :: Python :: 3.11
Requires-Dist: matplotlib (>=3.7,<4.0)
Project-URL: Documentation, https://patricknraanes.github.io/mpl-tools
Project-URL: Repository, https://github.com/patricknraanes/mpl-tools
